wudao_dict_plus-3.4.0.dist-info/METADATA
wudao_dict_plus-3.4.0.dist-info/WHEEL
wudao_dict_plus-3.4.0.dist-info/entry_points.txt
wudao_dict/__init__.py
wudao_dict/cli.py
wudao_dict/client.py
wudao_dict/draw.py
wudao_dict/server.py
wudao_dict/utils.py
wudao_dict/core/__init__.py
wudao_dict/core/config.py
wudao_dict/core/interface.py
wudao_dict/dict/__init__.py
wudao_dict/dict/local.py
wudao_dict/dict/youdao/__init__.py
wudao_dict/dict/youdao/youdao.py
wudao_dict/res/__init__.py
wudao_dict/res/dict.db.zst
wudao_dict_plus-3.4.0.dist-info/RECORD
