Metadata-Version: 2.1
Name: wudao-dict-plus
Version: 3.4.0
Summary: 无道词典增强版。对原有的无道词典的功能进行了修复和增强。
Keywords: dictionary,command-line
Maintainer-Email: Syize <syizeliu@gmail.com>
Project-URL: homepage, https://github.com/Syize/Wudao-dict-plus
Project-URL: repository, https://github.com/Syize/Wudao-dict-plus
Project-URL: documentation, https://github.com/Syize/Wudao-dict-plus
Project-URL: Bug Tracker, https://github.com/Syize/Wudao-dict-plus/issues
Requires-Python: >=3.8
Requires-Dist: beautifulsoup4>=4.14.3
Requires-Dist: lxml>=6.0.2
Requires-Dist: platformdirs>=4.3.6
Requires-Dist: requests>=2.32.4
Requires-Dist: rich>=14.2.0
Requires-Dist: zstandard>=0.23.0
